typed_stream/__init__.py
typed_stream/__main__.py
typed_stream/exceptions.py
typed_stream/functions.py
typed_stream/py.typed
typed_stream/streamable.py
typed_stream/version.py
typed_stream/_impl/__init__.py
typed_stream/_impl/_default_value.py
typed_stream/_impl/_iteration_utils.py
typed_stream/_impl/_lazy_file_iterators.py
typed_stream/_impl/_types.py
typed_stream/_impl/_typing.py
typed_stream/_impl/_utils.py
typed_stream/_impl/file_streams.py
typed_stream/_impl/functions.py
typed_stream/_impl/stream.py
typed_stream/_impl/stream_abc.py
typed_stream-0.155.0.dist-info/entry_points.txt
typed_stream-0.155.0.dist-info/licenses/LICENSE
typed_stream-0.155.0.dist-info/WHEEL
typed_stream-0.155.0.dist-info/METADATA
typed_stream-0.155.0.dist-info/RECORD
